README.rst
setup.py
TheCannon/__init__.py
TheCannon/apogee.py
TheCannon/dataset.py
TheCannon/find_continuum_pixels.py
TheCannon/infer_labels.py
TheCannon/lamost.py
TheCannon/model.py
TheCannon/normalization.py
TheCannon/train_model.py
TheCannon.egg-info/PKG-INFO
TheCannon.egg-info/SOURCES.txt
TheCannon.egg-info/dependency_links.txt
TheCannon.egg-info/top_level.txt
TheCannon/helpers/__init__.py
TheCannon/helpers/compatibility.py
TheCannon/helpers/fits.py
TheCannon/helpers/simpletable.py
TheCannon/helpers/corner/__init__.py
TheCannon/helpers/corner/corner.py