Metadata-Version: 1.0
Name: TheCannon
Version: 0.7.1
Summary: Data-driven stellar parameters and abundances from spectra
Home-page: http://github.com/annayqho/TheCannon
Author: Anna Y. Q. Ho
Author-email: annayqho@gmail.com
License: MIT
Platform: UNKNOWN
